saltax/README.md
saltax/__init__.py
saltax/contexts.py
saltax/instructions/README.md
saltax/instructions/__init__.py
saltax/instructions/generator.py
saltax/match/README.md
saltax/match/__init__.py
saltax/match/match.py
saltax/match/utils.py
saltax/match/visual.py
saltax/patches/README.md
saltax/patches/__init__.py
saltax/patches/straxen_2.py
saltax/patches/straxen_3.py
saltax/plugins/README.md
saltax/plugins/__init__.py
saltax/plugins/csv_input.py
saltax/plugins/peaklets.py
saltax/plugins/raw_records.py
saltax/plugins/records.py
saltax/test_utils.py
saltax/utils.py
saltax-0.2.3.dist-info/METADATA
saltax-0.2.3.dist-info/WHEEL
saltax-0.2.3.dist-info/licenses/LICENSE
saltax-0.2.3.dist-info/RECORD
