Metadata-Version: 2.4
Name: saltax
Version: 0.2.3
Summary: Salting MC into straxen
License-File: LICENSE
Author: Lanqing Yuan
Requires-Python: >=3.9,<3.13
Classifier: Development Status :: 3 - Alpha
Classifier: Intended Audience :: Science/Research
Classifier: License :: OSI Approved :: MIT License
Classifier: Natural Language :: English
Classifier: Programming Language :: Python :: 3
Classifier: Programming Language :: Python :: 3.9
Classifier: Programming Language :: Python :: 3.10
Classifier: Programming Language :: Python :: 3.11
Classifier: Programming Language :: Python :: 3.12
Classifier: Programming Language :: Python :: Implementation :: CPython
Classifier: Topic :: Scientific/Engineering :: Physics
Requires-Dist: numba
Requires-Dist: numpy
Requires-Dist: pandas
Requires-Dist: scipy
Requires-Dist: strax
Requires-Dist: straxen
Requires-Dist: tabulate
Requires-Dist: xenon-fuse (>=1.5.4,<1.5.7)
Project-URL: Repository, https://github.com/XENONnT/saltax
